fpowerkit/__init__.py
fpowerkit/bus.py
fpowerkit/cases.py
fpowerkit/ess.py
fpowerkit/gen.py
fpowerkit/grid.py
fpowerkit/island.py
fpowerkit/line.py
fpowerkit/lpwrapper.py
fpowerkit/pvwind.py
fpowerkit/solbase.py
fpowerkit/solcmb.py
fpowerkit/solcvx.py
fpowerkit/soldist.py
fpowerkit/soldss.py
fpowerkit/solldf.py
fpowerkit/solldf2.py
fpowerkit/solnt.py
fpowerkit/utils.py
fpowerkit-0.4.0.dist-info/METADATA
fpowerkit-0.4.0.dist-info/WHEEL
fpowerkit-0.4.0.dist-info/licenses/LICENSE
fpowerkit-0.4.0.dist-info/RECORD
