Metadata-Version: 2.4
Name: fpowerkit
Version: 0.4.0
Summary: A PDN solver with multiple solutions.
Author: fmy-xfk
License-Expression: MIT
License-File: LICENSE
Classifier: License :: OSI Approved :: MIT License
Classifier: Operating System :: OS Independent
Classifier: Programming Language :: Python :: 3
Requires-Python: >=3.8
Requires-Dist: feasytools>=0.0.21
Requires-Dist: numpy>=1.19.0
Provides-Extra: distflow
Requires-Dist: cvxpy; extra == 'distflow'
Requires-Dist: ecos; extra == 'distflow'
Provides-Extra: dss
Requires-Dist: py-dss-interface; extra == 'dss'
Provides-Extra: full
Requires-Dist: cvxpy; extra == 'full'
Requires-Dist: ecos; extra == 'full'
Requires-Dist: py-dss-interface; extra == 'full'
Provides-Extra: ldf
Requires-Dist: scipy; extra == 'ldf'
